{
  "7355719857": {
    "id": 7355719857,
    "username": "Tried_12",
    "first_name": "Md Babuâ–ªï¸",
    "last_name": "Sarkar",
    "first_seen": "2025-11-05T02:34:00.379944",
    "last_seen": "2025-11-05T03:34:43.858077",
    "command_count": 0
  },
  "6393419765": {
    "id": 6393419765,
    "username": "RL_Rakib_Hasan",
    "first_name": "Â Rakib hasan",
    "last_name": null,
    "first_seen": "2025-11-05T02:57:10.879230",
    "last_seen": "2025-11-06T12:18:18.103230",
    "command_count": 24
  },
  "6875606208": {
    "id": 6875606208,
    "username": "Rakib_ADMIN07",
    "first_name": "mahim hasan rafi",
    "last_name": null,
    "first_seen": "2025-11-05T03:04:17.940811",
    "last_seen": "2025-11-05T03:04:17.940811",
    "command_count": 0
  },
  "7559496726": {
    "id": 7559496726,
    "username": "hrhayat85",
    "first_name": "ÊœÊ€.Êœá´€Êá´€á´›âœ¨ï¸",
    "last_name": null,
    "first_seen": "2025-11-05T15:23:09.490063",
    "last_seen": "2025-11-05T15:23:09.490063",
    "command_count": 0
  },
  "6928627559": {
    "id": 6928627559,
    "username": "Cbvcjfhgggg",
    "first_name": "Hasmiâ–ªï¸",
    "last_name": null,
    "first_seen": "2025-11-05T16:31:32.209257",
    "last_seen": "2025-11-05T16:31:42.757964",
    "command_count": 0
  },
  "7127437250": {
    "id": 7127437250,
    "username": null,
    "first_name": "Nupor",
    "last_name": null,
    "first_seen": "2025-11-05T16:32:23.185241",
    "last_seen": "2025-11-05T16:32:57.891139",
    "command_count": 0
  },
  "5830077425": {
    "id": 5830077425,
    "username": "SN_SAKiB_SN",
    "first_name": "âœ¿ï¸ğš‚ğ™°ğ™ºğ™¸ğ™±â¦ï¸",
    "last_name": "ğ™·ğ™°ğš‚ğ™°ğ™½",
    "first_seen": "2025-11-06T12:15:42.177910",
    "last_seen": "2025-11-06T12:15:42.177910",
    "command_count": 0
  },
  "7371166435": {
    "id": 7371166435,
    "username": null,
    "first_name": "Sakib",
    "last_name": null,
    "first_seen": "2025-11-06T12:33:37.676812",
    "last_seen": "2025-11-06T12:33:37.676812",
    "command_count": 0
  }
}